test2doc/__init__.py
test2doc/base.py
test2doc/tests/__init__.py
test2doc/tests/base_test.py
test2doc-0.0.2.dist-info/LICENSE
test2doc-0.0.2.dist-info/METADATA
test2doc-0.0.2.dist-info/WHEEL
test2doc-0.0.2.dist-info/top_level.txt
test2doc-0.0.2.dist-info/RECORD
