Metadata-Version: 2.1
Name: test2doc
Version: 0.0.2
Summary: Generate documentation from tests
Home-page: https://github.com/i2mint/test2doc
Author: OtoSense
License: apache-2.0
Platform: any
